janus/__init__.py
janus/agent_settings.py
janus/app.py
janus/settings.py
janus/api/__init__.py
janus/api/agent.py
janus/api/ansible_job.py
janus/api/controller.py
janus/api/db.py
janus/api/endpoints_api.py
janus/api/models.py
janus/api/portainer_docker.py
janus/api/query.py
janus/api/utils.py
janus/api/validator.py
janus/api/sys/__init__.py
janus/api/sys/cpu.py
janus/api/sys/disk.py
janus/api/sys/mem.py
janus/api/sys/net.py
janus/api/sys/numa.py
janus/api/sys/sysctl.py
janus/api/sys/tc.py
janus/config/janus.conf.example
janus/config/logging.conf
janus/config/profiles/ansible.yaml
janus/config/profiles/features.yaml
janus/config/profiles/profiles.yaml
janus/config/profiles/qos.yaml
janus/config/profiles/test-profile.yaml
janus/config/profiles/volumes.yaml
janus/lib/__init__.py
janus/lib/agent_monitor.py
janus_dtnaas-0.2.post10.dist-info/LICENSE
janus_dtnaas-0.2.post10.dist-info/METADATA
janus_dtnaas-0.2.post10.dist-info/WHEEL
janus_dtnaas-0.2.post10.dist-info/entry_points.txt
janus_dtnaas-0.2.post10.dist-info/top_level.txt
janus_dtnaas-0.2.post10.dist-info/RECORD
