Metadata-Version: 2.1
Name: janus-dtnaas
Version: 0.2.post10
Summary: Janus DTNaaS Controller
Home-page: https://github.com/esnet/janus
Author: Ezra Kissel
Author-email: kissel@es.net
Keywords: Janus Controller
Classifier: Programming Language :: Python :: 3
Classifier: Topic :: Software Development :: Libraries :: Application Frameworks
Classifier: License :: OSI Approved :: BSD License
Classifier: Operating System :: OS Independent
Requires-Python: >=3.7
License-File: LICENSE
Requires-Dist: cryptography
Requires-Dist: Flask (==2.0.2)
Requires-Dist: flask-restplus (==0.13.0)
Requires-Dist: Flask-httpauth (==4.4.0)
Requires-Dist: numa
Requires-Dist: portainer-api
Requires-Dist: psutil
Requires-Dist: py-cpuinfo
Requires-Dist: pyyaml
Requires-Dist: requests
Requires-Dist: six
Requires-Dist: tinydb
Requires-Dist: virtfs
Requires-Dist: tcconfig
Requires-Dist: Werkzeug (==2.0.2)
Requires-Dist: pydantic (==1.9.0)
Requires-Dist: ansible-tower-cli
